README.rst
setup.py
Spacy2FoLiA.egg-info/PKG-INFO
Spacy2FoLiA.egg-info/SOURCES.txt
Spacy2FoLiA.egg-info/dependency_links.txt
Spacy2FoLiA.egg-info/entry_points.txt
Spacy2FoLiA.egg-info/requires.txt
Spacy2FoLiA.egg-info/top_level.txt
spacy2folia/__init__.py
spacy2folia/spacy2folia.py