Metadata-Version: 2.1
Name: Spacy2FoLiA
Version: 0.3.3
Summary: Library that adds FoLiA (format for linguistic annotation) support to spaCy
Home-page: https://proycon.github.io/folia
Author: Maarten van Gompel
Author-email: proycon@anaproy.nl
License: GPL
Keywords: nlp computational_linguistics spacy linguistics toolkit folia
Platform: UNKNOWN
Classifier: Development Status :: 5 - Production/Stable
Classifier: Topic :: Text Processing :: Linguistic
Classifier: Programming Language :: Python :: 3
Classifier: Operating System :: POSIX
Classifier: Intended Audience :: Developers
Classifier: Intended Audience :: Science/Research
Classifier: License :: OSI Approved :: GNU General Public License v3 (GPLv3)
